setup.cfg
setup.py
godity/engine.py
godity/inputs.py
godity.egg-info/PKG-INFO
godity.egg-info/SOURCES.txt
godity.egg-info/dependency_links.txt
godity.egg-info/top_level.txt
godity/components/Animation.py
godity/components/BoxCollider.py
godity/components/Camera.py
godity/components/Light.py
godity/components/Rigidbody.py
godity/components/SpriteRenderer.py
godity/components/Tilemap.py
godity/components/Transform.py
godity/components/__init__.py
godity/core/App.py
godity/core/Component.py
godity/core/Entity.py
godity/core/Layer.py
godity/core/Scene.py
godity/core/Timer.py
godity/core/Window.py
godity/core/__init__.py
godity/math/Vector2.py
godity/math/__init__.py