Metadata-Version: 1.0
Name: godity
Version: 0.9
Summary: A simple framework to create 2D games!
Home-page: https://github.com/samueldev45/GodityEngine
Author: Samuel Andrade
Author-email: samueldeveloper45@gmail.com
License: MIT
Keywords: game engine,framework
Platform: UNKNOWN
